llm_eval/__init__.py
llm_eval/evaluator.py
llm_evaluation-0.0.3.dist-info/METADATA
llm_evaluation-0.0.3.dist-info/WHEEL
llm_evaluation-0.0.3.dist-info/top_level.txt
llm_evaluation-0.0.3.dist-info/RECORD
