Metadata-Version: 2.1
Name: llm-evaluation
Version: 0.0.3
Summary: LLM Evaluation Package
Author: Maks Lupey
Author-email: <maxrty234@gmail.com>
Keywords: python,llm,evaluation,llm evaluation
Classifier: Development Status :: 1 - Planning
Classifier: Intended Audience :: Developers
Classifier: Programming Language :: Python :: 3
Classifier: Operating System :: Unix
Classifier: Operating System :: MacOS :: MacOS X
Classifier: Operating System :: Microsoft :: Windows
Requires-Dist: langfuse
Requires-Dist: openai
Requires-Dist: langchain_openai
Requires-Dist: langchain
Requires-Dist: rapidfuzz
Requires-Dist: scikit-learn
Requires-Dist: llama-index-llms-openai-like
